imgs/__init__.py
imgs/__main__.py
imgs/image.py
imgs/imgs.py
imgs/py.typed
imgs-0.1.4.dist-info/METADATA
imgs-0.1.4.dist-info/WHEEL
imgs-0.1.4.dist-info/entry_points.txt
imgs-0.1.4.dist-info/licenses/LICENSE
imgs-0.1.4.dist-info/RECORD
