Metadata-Version: 2.4
Name: imgs
Version: 0.1.4
Summary: changeme
Project-URL: Repository, https://github.com/leo1oel/imgs
Author-email: leo <liuym23@mails.tsinghua.edu.cn>
License-Expression: MIT
License-File: LICENSE
Classifier: Development Status :: 4 - Beta
Classifier: Intended Audience :: Developers
Classifier: Operating System :: OS Independent
Classifier: Programming Language :: Python
Classifier: Programming Language :: Python :: 3
Classifier: Programming Language :: Python :: 3.11
Classifier: Programming Language :: Python :: 3.12
Classifier: Programming Language :: Python :: 3.13
Classifier: Typing :: Typed
Requires-Python: <4.0,>=3.11
Requires-Dist: imageio[tifffile]>=2.37.0
Requires-Dist: matplotlib>=3.10.5
